[
    {
        "i": "279304",
        "rank": 20,
        "cnt": 1660,
        "gap": 0,
        "title": "대충생긴얼굴",
        "user": "리부트/오타쿠포비아"
    },
    {
        "i": "278349",
        "rank": 38,
        "cnt": 899,
        "gap": -1,
        "title": "호문쿨루 성형",
        "user": "제니스/민트카닉"
    },
    {
        "i": "280735",
        "rank": 33,
        "cnt": 1072,
        "gap": -2,
        "title": "코가 대단한 얼굴",
        "user": "루나/움징어"
    },
    {
        "i": "281064",
        "rank": 29,
        "cnt": 1209,
        "gap": 0,
        "title": "앙큼냥 & 용맹냥 얼굴",
        "user": "루나/무너끙"
    },
    {
        "i": "277977",
        "rank": 3,
        "cnt": 4904,
        "gap": 0,
        "title": "어제 울었어 얼굴",
        "user": "엘리시움/Babu"
    },
    {
        "i": "280767",
        "rank": 35,
        "cnt": 988,
        "gap": 0,
        "title": "저거 사줘 얼굴",
        "user": "크로아/소인바람"
    },
    {
        "i": "277462",
        "rank": 25,
        "cnt": 1492,
        "gap": 0,
        "title": "츄르 얼굴",
        "user": "이노시스/겨드래곤"
    },
    {
        "i": "278619",
        "rank": 15,
        "cnt": 1973,
        "gap": 0,
        "title": "다이아 얼굴",
        "user": "루나/쌈영호"
    },
    {
        "i": "280800",
        "rank": 21,
        "cnt": 1633,
        "gap": 0,
        "title": "단추인형 얼굴",
        "user": "루나/Marlboro멜론"
    },
    {
        "i": "276355",
        "rank": 16,
        "cnt": 1891,
        "gap": 0,
        "title": "멈한 멀굴",
        "user": "크로아/박수혁"
    },
    {
        "i": "277415",
        "rank": 4,
        "cnt": 4407,
        "gap": 0,
        "title": "물기 스며든 얼굴",
        "user": "스카니아/링크카인조아"
    },
    {
        "i": "279505",
        "rank": 14,
        "cnt": 2042,
        "gap": 0,
        "title": "볼매얼굴",
        "user": "엘리시움/밝을밤"
    },
    {
        "i": "277220",
        "rank": 42,
        "cnt": 838,
        "gap": 6,
        "title": "순수 꼬마, 새침 꼬마 얼굴",
        "user": "루나/새밤"
    },
    {
        "i": "280774",
        "rank": 27,
        "cnt": 1300,
        "gap": 0,
        "title": "울망졸망 얼굴",
        "user": "오로라/솔찌짭"
    },
    {
        "i": "278617",
        "rank": 12,
        "cnt": 2293,
        "gap": 0,
        "title": "장난꾸러기 얼굴",
        "user": "베라/레이더퍼스트"
    },
    {
        "i": "281092",
        "rank": 7,
        "cnt": 3668,
        "gap": 0,
        "title": "청명 얼굴",
        "user": "루나/은새콩"
    }
]